incremental_trees/__init__.py
incremental_trees/add_ins/__init__.py
incremental_trees/add_ins/classifier_additions.py
incremental_trees/add_ins/classifier_overloads.py
incremental_trees/add_ins/forest_additions.py
incremental_trees/add_ins/forest_overloads.py
incremental_trees/add_ins/regressor_additions.py
incremental_trees/add_ins/regressor_overloads.py
incremental_trees/add_ins/sklearn_overloads.py
incremental_trees/models/__init__.py
incremental_trees/models/classification/__init__.py
incremental_trees/models/classification/streaming_extc.py
incremental_trees/models/classification/streaming_rfc.py
incremental_trees/models/regression/__init__.py
incremental_trees/models/regression/streaming_extr.py
incremental_trees/models/regression/streaming_rfr.py
scripts/__init__.py
scripts/example_dask.py
scripts/example_fit.py
scripts/example_partial_fit.py
tests/__init__.py
tests/common/__init__.py
tests/common/data_fixture.py
tests/common/param_fixtures.py
tests/integration/__init__.py
tests/integration/base/__init__.py
tests/integration/base/class_consistency_test_base.py
tests/integration/base/dask_test_base.py
tests/integration/base/fit_test_base.py
tests/integration/base/partial_fit_test_base.py
tests/integration/base/predict_test_base.py
tests/integration/classification/__init__.py
tests/integration/classification/test_streaming_extc.py
tests/integration/classification/test_streaming_rfc.py
tests/integration/regression/__init__.py
tests/integration/regression/test_streaming_extr.py
tests/integration/regression/test_streaming_rfr.py
tests/performance/__init__.py
tests/performance/test_benchmarks.py
tests/performance/test_grids.py
tests/unit/__init__.py
incremental_trees-0.6.0.dist-info/LICENSE
incremental_trees-0.6.0.dist-info/METADATA
incremental_trees-0.6.0.dist-info/WHEEL
incremental_trees-0.6.0.dist-info/top_level.txt
incremental_trees-0.6.0.dist-info/RECORD
