Metadata-Version: 2.1
Name: incremental-trees
Version: 0.6.0
Summary: Sklearn forests with partial fits
Home-page: https://github.com/garethjns/IncrementalTrees
Author: Gareth Jones
Author-email: garethgithub@gmail.com
Requires-Python: >=3.8
License-File: LICENSE
Requires-Dist: scikit-learn (==1.2)
Requires-Dist: pandas
Requires-Dist: numpy
Requires-Dist: dask (==2022.12)
Requires-Dist: dask-glm (==0.2.0)
Requires-Dist: dask-ml (==2022.5.27)
Requires-Dist: fsspec
